[
    {
        "id": "a21205b04a036fd3",
        "type": "tab",
        "label": "Flow 1",
        "disabled": false,
        "info": "",
        "env": []
    },
    {
        "id": "329623213bc977e6",
        "type": "tab",
        "label": "Flow 2",
        "disabled": false,
        "info": "",
        "env": []
    },
    {
        "id": "51f972a5289809dd",
        "type": "mqtt-broker",
        "name": "",
        "broker": "localhost",
        "port": "1883",
        "clientid": "",
        "autoConnect": true,
        "usetls": false,
        "protocolVersion": "4",
        "keepalive": "60",
        "cleansession": true,
        "birthTopic": "",
        "birthQos": "0",
        "birthPayload": "",
        "birthMsg": {},
        "closeTopic": "",
        "closeQos": "0",
        "closePayload": "",
        "closeMsg": {},
        "willTopic": "",
        "willQos": "0",
        "willPayload": "",
        "willMsg": {},
        "userProps": "",
        "sessionExpiry": ""
    },
    {
        "id": "68f736de8349ca08",
        "type": "mqtt-broker",
        "name": "",
        "broker": "27cc61dbaffc4da08cd0081cabd8cf01.s2.eu.hivemq.cloud",
        "port": "8883",
        "tls": "",
        "clientid": "",
        "autoConnect": true,
        "usetls": true,
        "protocolVersion": "5",
        "keepalive": "60",
        "cleansession": true,
        "birthTopic": "",
        "birthQos": "0",
        "birthPayload": "",
        "birthMsg": {},
        "closeTopic": "",
        "closeQos": "0",
        "closePayload": "",
        "closeMsg": {},
        "willTopic": "",
        "willQos": "0",
        "willPayload": "",
        "willMsg": {},
        "userProps": "",
        "sessionExpiry": ""
    },
    {
        "id": "cb41d6448b9144b4",
        "type": "ui_tab",
        "name": "Home",
        "icon": "dashboard",
        "disabled": false,
        "hidden": false
    },
    {
        "id": "d0bef61d91d02da5",
        "type": "ui_base",
        "theme": {
            "name": "theme-light",
            "lightTheme": {
                "default": "#0094CE",
                "baseColor": "#0094CE",
                "baseFont": "-apple-system,BlinkMacSystemFont,Segoe UI,Roboto,Oxygen-Sans,Ubuntu,Cantarell,Helvetica Neue,sans-serif",
                "edited": false
            },
            "darkTheme": {
                "default": "#097479",
                "baseColor": "#097479",
                "baseFont": "-apple-system,BlinkMacSystemFont,Segoe UI,Roboto,Oxygen-Sans,Ubuntu,Cantarell,Helvetica Neue,sans-serif",
                "edited": false
            },
            "customTheme": {
                "name": "Untitled Theme 1",
                "default": "#4B7930",
                "baseColor": "#4B7930",
                "baseFont": "-apple-system,BlinkMacSystemFont,Segoe UI,Roboto,Oxygen-Sans,Ubuntu,Cantarell,Helvetica Neue,sans-serif"
            },
            "themeState": {
                "base-color": {
                    "default": "#0094CE",
                    "value": "#0094CE",
                    "edited": false
                },
                "page-titlebar-backgroundColor": {
                    "value": "#0094CE",
                    "edited": false
                },
                "page-backgroundColor": {
                    "value": "#fafafa",
                    "edited": false
                },
                "page-sidebar-backgroundColor": {
                    "value": "#ffffff",
                    "edited": false
                },
                "group-textColor": {
                    "value": "#1bbfff",
                    "edited": false
                },
                "group-borderColor": {
                    "value": "#ffffff",
                    "edited": false
                },
                "group-backgroundColor": {
                    "value": "#ffffff",
                    "edited": false
                },
                "widget-textColor": {
                    "value": "#111111",
                    "edited": false
                },
                "widget-backgroundColor": {
                    "value": "#0094ce",
                    "edited": false
                },
                "widget-borderColor": {
                    "value": "#ffffff",
                    "edited": false
                },
                "base-font": {
                    "value": "-apple-system,BlinkMacSystemFont,Segoe UI,Roboto,Oxygen-Sans,Ubuntu,Cantarell,Helvetica Neue,sans-serif"
                }
            },
            "angularTheme": {
                "primary": "indigo",
                "accents": "blue",
                "warn": "red",
                "background": "grey",
                "palette": "light"
            }
        },
        "site": {
            "name": "Node-RED Dashboard",
            "hideToolbar": "false",
            "allowSwipe": "false",
            "lockMenu": "false",
            "allowTempTheme": "true",
            "dateFormat": "DD/MM/YYYY",
            "sizes": {
                "sx": 48,
                "sy": 48,
                "gx": 6,
                "gy": 6,
                "cx": 6,
                "cy": 6,
                "px": 0,
                "py": 0
            }
        }
    },
    {
        "id": "67e58d45e03259b7",
        "type": "ui_group",
        "name": "Default",
        "tab": "cb41d6448b9144b4",
        "order": 1,
        "disp": true,
        "width": "6",
        "collapse": false,
        "className": ""
    },
    {
        "id": "8a012318a4608c51",
        "type": "mqtt in",
        "z": "a21205b04a036fd3",
        "name": "",
        "topic": "TD02_GP10/temp",
        "qos": "2",
        "datatype": "auto-detect",
        "broker": "68f736de8349ca08",
        "nl": false,
        "rap": true,
        "rh": 0,
        "inputs": 0,
        "x": 390,
        "y": 240,
        "wires": [
            [
                "3aaa74fe34a1189a"
            ]
        ]
    },
    {
        "id": "6b1d19f37779bf53",
        "type": "mqtt in",
        "z": "a21205b04a036fd3",
        "name": "",
        "topic": "TD02_GP10/relhum",
        "qos": "2",
        "datatype": "auto-detect",
        "broker": "68f736de8349ca08",
        "nl": false,
        "rap": true,
        "rh": 0,
        "inputs": 0,
        "x": 390,
        "y": 440,
        "wires": [
            [
                "173b746dd107b25c"
            ]
        ]
    },
    {
        "id": "173b746dd107b25c",
        "type": "ui_gauge",
        "z": "a21205b04a036fd3",
        "name": "",
        "group": "67e58d45e03259b7",
        "order": 0,
        "width": 0,
        "height": 0,
        "gtype": "gage",
        "title": "Humidité",
        "label": "%",
        "format": "{{value}}",
        "min": "0",
        "max": "100",
        "colors": [
            "#00b500",
            "#e6e600",
            "#ca3838"
        ],
        "seg1": "",
        "seg2": "",
        "diff": false,
        "className": "",
        "x": 660,
        "y": 240,
        "wires": []
    },
    {
        "id": "3aaa74fe34a1189a",
        "type": "ui_chart",
        "z": "a21205b04a036fd3",
        "name": "",
        "group": "67e58d45e03259b7",
        "order": 1,
        "width": 0,
        "height": 0,
        "label": "Température (°C)",
        "chartType": "line",
        "legend": "false",
        "xformat": "HH:mm:ss",
        "interpolate": "linear",
        "nodata": "",
        "dot": false,
        "ymin": "10",
        "ymax": "30",
        "removeOlder": 1,
        "removeOlderPoints": "",
        "removeOlderUnit": "3600",
        "cutout": 0,
        "useOneColor": false,
        "useUTC": false,
        "colors": [
            "#1f77b4",
            "#aec7e8",
            "#ff7f0e",
            "#2ca02c",
            "#98df8a",
            "#d62728",
            "#ff9896",
            "#9467bd",
            "#c5b0d5"
        ],
        "outputs": 1,
        "useDifferentColor": false,
        "className": "",
        "x": 710,
        "y": 360,
        "wires": [
            []
        ]
    }
]